BayesOpt4dftu/core.py
BayesOpt4dftu/special_kpath.py
BayesOpt4dftu-0.1.4.dist-info/LICENSE
BayesOpt4dftu-0.1.4.dist-info/METADATA
BayesOpt4dftu-0.1.4.dist-info/WHEEL
BayesOpt4dftu-0.1.4.dist-info/top_level.txt
BayesOpt4dftu-0.1.4.dist-info/RECORD
