Metadata-Version: 2.1
Name: BayesOpt4dftu
Version: 0.1.4
Summary: UNKNOWN
Home-page: https://github.com/maituoy/BayesianOpt4dftu
Author: Maituo Yu
License: UNKNOWN
Platform: UNKNOWN
License-File: LICENSE
Requires-Dist: numpy
Requires-Dist: ase (==3.22.0)
Requires-Dist: pymatgen (==2022.0.16)
Requires-Dist: bayesian-optimization (==1.2.0)
Requires-Dist: pandas
Requires-Dist: vaspvis (==1.2.2)
